odoo8_addon_account_payment_sale-8.0.1.0.0.99.dev17-py3.8-nspkg.pth
odoo_addons/account_payment_sale/README.rst
odoo_addons/account_payment_sale/__init__.py
odoo_addons/account_payment_sale/__openerp__.py
odoo_addons/account_payment_sale/i18n/account_payment_sale.pot
odoo_addons/account_payment_sale/i18n/ca.po
odoo_addons/account_payment_sale/i18n/de.po
odoo_addons/account_payment_sale/i18n/es.po
odoo_addons/account_payment_sale/i18n/es_ES.po
odoo_addons/account_payment_sale/i18n/fi.po
odoo_addons/account_payment_sale/i18n/fr.po
odoo_addons/account_payment_sale/i18n/hr.po
odoo_addons/account_payment_sale/i18n/hu.po
odoo_addons/account_payment_sale/i18n/it.po
odoo_addons/account_payment_sale/i18n/nl.po
odoo_addons/account_payment_sale/i18n/nl_NL.po
odoo_addons/account_payment_sale/i18n/pt_BR.po
odoo_addons/account_payment_sale/i18n/ro.po
odoo_addons/account_payment_sale/i18n/sk.po
odoo_addons/account_payment_sale/i18n/sl.po
odoo_addons/account_payment_sale/i18n/tr.po
odoo_addons/account_payment_sale/i18n/tr_TR.po
odoo_addons/account_payment_sale/i18n/zh_CN.po
odoo_addons/account_payment_sale/models/__init__.py
odoo_addons/account_payment_sale/models/sale_order.py
odoo_addons/account_payment_sale/static/description/icon.png
odoo_addons/account_payment_sale/views/sale_order_view.xml
odoo8_addon_account_payment_sale-8.0.1.0.0.99.dev17.dist-info/METADATA
odoo8_addon_account_payment_sale-8.0.1.0.0.99.dev17.dist-info/WHEEL
odoo8_addon_account_payment_sale-8.0.1.0.0.99.dev17.dist-info/namespace_packages.txt
odoo8_addon_account_payment_sale-8.0.1.0.0.99.dev17.dist-info/top_level.txt
odoo8_addon_account_payment_sale-8.0.1.0.0.99.dev17.dist-info/RECORD
